LICENSE
MANIFEST.in
README
setup.py
dojango/__init__.py
dojango/context_processors.py
dojango/decorators.py
dojango/middleware.py
dojango/models.py
dojango/urls.py
dojango/version.py
dojango/views.py
dojango.egg-info/PKG-INFO
dojango.egg-info/SOURCES.txt
dojango.egg-info/dependency_links.txt
dojango.egg-info/not-zip-safe
dojango.egg-info/top_level.txt
dojango/appengine/README
dojango/appengine/__init__.py
dojango/appengine/dojo_serve.py
dojango/appengine/memcache_zipserve.py
dojango/bin/dojobuild.py
dojango/conf/__init__.py
dojango/conf/settings.py
dojango/contrib/__init__.py
dojango/contrib/auth/__init__.py
dojango/contrib/auth/forms.py
dojango/data/__init__.py
dojango/data/modelstore/__init__.py
dojango/data/modelstore/exceptions.py
dojango/data/modelstore/fields.py
dojango/data/modelstore/methods.py
dojango/data/modelstore/services.py
dojango/data/modelstore/stores.py
dojango/data/modelstore/treestore.py
dojango/data/modelstore/utils.py
dojango/data/piston/__init__.py
dojango/data/piston/emitters.py
dojango/dojo-media/dojango.profile.js
dojango/dojo-media/dojango_optimized.profile.js
dojango/dojo-media/dojango/_base.js
dojango/dojo-media/dojango/dojango.js
dojango/dojo-media/dojango/form/Form.js
dojango/dojo-media/dojango/resources/arrowSmall.gif
dojango/dojo-media/dojango/resources/blank.html
dojango/dojo-media/dojango/resources/dojango_logo.jpg
dojango/dojo-media/dojango/resources/note.gif
dojango/dojo-media/dojango/resources/tube.gif
dojango/dojo-media/dojango/resources/tubeTall.gif
dojango/dojo-media/dojango/widget/ThumbnailPicker.js
dojango/dojo-media/dojango/widget/plugins/InsertImage.js
dojango/dojo-media/dojango/widget/resources/ThumbnailPicker.css
dojango/dojo-media/src/empty.txt
dojango/forms/__init__.py
dojango/forms/fields.py
dojango/forms/formsets.py
dojango/forms/models.py
dojango/forms/widgets.py
dojango/management/__init__.py
dojango/management/commands/__init__.py
dojango/management/commands/dojobuild.py
dojango/management/commands/dojoload.py
dojango/templates/dojango/base.html
dojango/templates/dojango/base_i18n.html
dojango/templates/dojango/include.html
