Metadata-Version: 1.1
Name: dojango
Version: 0.5.8
Summary: Reusable django application that helps you to use the client-side framework dojo
Home-page: http://code.google.com/p/dojango/
Author: Tobias von Klipstein
Author-email: tk@uxebu.com
License: License :: OSI Approved :: BSD License
Keywords: dojo,django,dojango,javascript
Platform: UNKNOWN
Classifier: Programming Language :: Python
Classifier: Topic :: Software Development :: Libraries :: Python Modules
Classifier: Framework :: Django
Classifier: Environment :: Web Environment
